[{"Name":"Mini Splatling","reKit":"False","Sub":null,"Special":null,"Class":"Splatling"},
{"Name":"Zink Mini Splatling","reKit":"True","Sub":null,"Special":null,"Class":"Splatling"},
{"Name":"Mini Splatling RTL-R","reKit":"True","Sub":null,"Special":null,"Class":"Splatling"},
{"Name":"Heavy Splatling","reKit":"False","Sub":null,"Special":null,"Class":"Splatling"},
{"Name":"Heavy Splatling Deco","reKit":"True","Sub":null,"Special":null,"Class":"Splatling"},
{"Name":"Hydra Splatling","reKit":"False","Sub":null,"Special":null,"Class":"Splatling"},
{"Name":"Custom Hydra Splatling","reKit":"True","Sub":null,"Special":null,"Class":"Splatling"},
{"Name":"Torrentz Hydra Splatling","reKit":"True","Sub":null,"Special":null,"Class":"Splatling"},
{"Name":"Nautilus 47","reKit":"False","Sub":null,"Special":null,"Class":"Splatling"},
{"Name":"Nautilus 79","reKit":"True","Sub":null,"Special":null,"Class":"Splatling"},
{"Name":"Ballpoint Splatling ","reKit":"False","Sub":null,"Special":null,"Class":"Splatling"},
{"Name":"Ballpoint Splatling Nouveau","reKit":"True","Sub":null,"Special":null,"Class":"Splatling"},
{"Name":"Heavy Edit Splatling","reKit":"False","Sub":null,"Special":null,"Class":"Splatling"},
{"Name":"Heavy Edit Splatling Nouveau","reKit":"True","Sub":null,"Special":null,"Class":"Splatling"},
{"Name":"Order Splatling Replica","reKit":"False","Sub":null,"Special":null,"Class":"Splatling"}]